{
    "Data": {
        "Pack": true,
        "Packed": [
            [
                [
                    200,
                    0
                ],
                [
                    175,
                    25
                ]
            ],
            [
                [
                    194,
                    6
                ],
                [
                    42,
                    158
                ]
            ],
            [
                [
                    198,
                    2
                ],
                [
                    102,
                    98
                ]
            ],
            [
                [
                    200,
                    0
                ],
                [
                    122,
                    78
                ]
            ],
            [
                [
                    195,
                    5
                ],
                [
                    37,
                    163
                ]
            ],
            [
                [
                    200,
                    0
                ],
                [
                    200,
                    0
                ]
            ],
            [
                [
                    200,
                    0
                ],
                [
                    153,
                    47
                ]
            ]
        ],
        "accuracy": [
            0.8585912585258484,
            0.9194236993789673,
            0.7315901517868042,
            0.7630736231803894,
            0.5490928292274475,
            0.9583777785301208,
            0.8815368413925171,
            0.9124866724014282,
            0.9298292398452759,
            0.9282283782958984,
            0.9247598648071289,
            0.9319637417793274,
            0.9023479223251343,
            0.93036288022995,
            0.9622023701667786,
            0.9794642925262451
        ],
        "conf_matrix": [
            [
                [
                    195,
                    5
                ],
                [
                    37,
                    163
                ]
            ],
            [
                [
                    200,
                    0
                ],
                [
                    47,
                    153
                ]
            ],
            [
                [
                    200,
                    0
                ],
                [
                    125,
                    75
                ]
            ],
            [
                [
                    199,
                    1
                ],
                [
                    66,
                    134
                ]
            ],
            [
                [
                    200,
                    0
                ],
                [
                    198,
                    2
                ]
            ],
            [
                [
                    200,
                    0
                ],
                [
                    21,
                    179
                ]
            ],
            [
                [
                    200,
                    0
                ],
                [
                    78,
                    122
                ]
            ],
            [
                [
                    200,
                    0
                ],
                [
                    79,
                    121
                ]
            ],
            [
                [
                    200,
                    0
                ],
                [
                    43,
                    157
                ]
            ],
            [
                [
                    200,
                    0
                ],
                [
                    74,
                    126
                ]
            ],
            [
                [
                    195,
                    5
                ],
                [
                    14,
                    186
                ]
            ],
            [
                [
                    197,
                    3
                ],
                [
                    39,
                    161
                ]
            ],
            [
                [
                    200,
                    0
                ],
                [
                    62,
                    138
                ]
            ],
            [
                [
                    200,
                    0
                ],
                [
                    20,
                    180
                ]
            ],
            [
                [
                    179,
                    1
                ],
                [
                    14,
                    166
                ]
            ],
            [
                [
                    180,
                    0
                ],
                [
                    6,
                    174
                ]
            ]
        ],
        "loss": [
            0.2199016172988509,
            0.12823780902671553,
            0.3493024631349465,
            0.30895897882336776,
            0.46376724619509824,
            0.07423149952366828,
            0.19769393227146612,
            0.14224005995389058,
            0.09986695917546558,
            0.1198820798061836,
            0.12546598156809946,
            0.11031683897428045,
            0.1584407617047274,
            0.0969226042635243,
            0.06817286009305483,
            0.0354117552723369
        ],
        "val_accuracy": [
            0.8949999809265137,
            0.8824999928474426,
            0.6875,
            0.8324999809265137,
            0.5049999952316284,
            0.9474999904632568,
            0.8050000071525574,
            0.8037499785423279,
            0.8912500143051147,
            0.8162500262260437,
            0.9537500143051147,
            0.8949999809265137,
            0.84375,
            0.949999988079071,
            0.9583333134651184,
            0.9819444417953491
        ],
        "val_loss": [
            0.14218518478097394,
            0.10918650681909639,
            0.310454264881555,
            0.22111626632511616,
            0.4055368547141552,
            0.06727073154050998,
            0.20569443262647838,
            0.19585226747309206,
            0.1220510751851907,
            0.17328003870659814,
            0.09142142025570138,
            0.14464452878479797,
            0.15986027283594012,
            0.0722392125056524,
            0.05941829137460554,
            0.03320386791052796
        ]
    },
    "callback": {
        "EarlyStopping": [
            {
                "baseline": null,
                "min_delta": 0,
                "mode": "auto",
                "monitor": "loss",
                "patience": 6,
                "restore_best_weights": false,
                "verbose": 0
            },
            {
                "baseline": null,
                "min_delta": 0,
                "mode": "auto",
                "monitor": "loss",
                "patience": 10,
                "restore_best_weights": false,
                "verbose": 0
            },
            {
                "baseline": null,
                "min_delta": 0,
                "mode": "auto",
                "monitor": "loss",
                "patience": 8,
                "restore_best_weights": false,
                "verbose": 0
            }
        ]
    },
    "compile": {
        "loss": [
            "binary_crossentropy"
        ],
        "loss_weights": [
            null
        ],
        "metrics": [
            [
                "accuracy"
            ]
        ],
        "run_eagerly": [
            false
        ],
        "weighted_metrics": [
            null
        ]
    },
    "iteration": {
        "#": [
            0
        ]
    },
    "model": {
        "class_weights": [
            [
                2.0,
                0.4
            ]
        ],
        "data": [
            [
                "N",
                "PN"
            ],
            [
                "N",
                "CV"
            ]
        ],
        "epoch": [
            5,
            50,
            2
        ],
        "save": [
            false
        ],
        "threshold": [
            0.0
        ]
    },
    "optimiser": {
        "beta_1": [
            0.9
        ],
        "beta_2": [
            0.999
        ],
        "decay": [
            1e-05
        ],
        "epsilon": [
            null
        ],
        "lr": [
            0.00065
        ],
        "name": [
            "Adam"
        ]
    }
}